{"lastUsed":1675252383419,"path":"F:\/Softwares\/jee-2022-12\/eclipse-workspace","projectCount":4,"recentFiles":[{"path":"\/JSPScriptlets\/src\/main\/webapp","parentWorkspace":"F:\/Softwares\/jee-2022-12\/eclipse-workspace","name":"scriptingElements.jsp","lastModified":1675248184935,"locationURI":"file:\/F:\/Softwares\/jee-2022-12\/eclipse-workspace\/JSPScriptlets\/src\/main\/webapp\/scriptingElements.jsp"},{"path":"\/JSPDirectives\/src\/main\/webapp","parentWorkspace":"F:\/Softwares\/jee-2022-12\/eclipse-workspace","name":"errorPage.jsp","lastModified":1675252251316,"locationURI":"file:\/F:\/Softwares\/jee-2022-12\/eclipse-workspace\/JSPDirectives\/src\/main\/webapp\/errorPage.jsp"},{"path":"\/StaticContentInJSP\/src\/main\/webapp\/js","parentWorkspace":"F:\/Softwares\/jee-2022-12\/eclipse-workspace","name":"helloJS.js","lastModified":1675078181472,"locationURI":"file:\/F:\/Softwares\/jee-2022-12\/eclipse-workspace\/StaticContentInJSP\/src\/main\/webapp\/js\/helloJS.js"},{"path":"\/JSPDirectives\/src\/main\/webapp","parentWorkspace":"F:\/Softwares\/jee-2022-12\/eclipse-workspace","name":"homePage.jsp","lastModified":1675252276802,"locationURI":"file:\/F:\/Softwares\/jee-2022-12\/eclipse-workspace\/JSPDirectives\/src\/main\/webapp\/homePage.jsp"},{"path":"\/JSPScriptlets\/src\/main\/webapp","parentWorkspace":"F:\/Softwares\/jee-2022-12\/eclipse-workspace","name":"jspWellFormed.jsp","lastModified":1675249305046,"locationURI":"file:\/F:\/Softwares\/jee-2022-12\/eclipse-workspace\/JSPScriptlets\/src\/main\/webapp\/jspWellFormed.jsp"},{"path":"\/StaticContentInJSP\/src\/main\/webapp","parentWorkspace":"F:\/Softwares\/jee-2022-12\/eclipse-workspace","name":"hello.jsp","lastModified":1675078584789,"locationURI":"file:\/F:\/Softwares\/jee-2022-12\/eclipse-workspace\/StaticContentInJSP\/src\/main\/webapp\/hello.jsp"},{"path":"\/StaticContentInJSP\/src\/main\/webapp\/css","parentWorkspace":"F:\/Softwares\/jee-2022-12\/eclipse-workspace","name":"helloCSS.css","lastModified":1675078423125,"locationURI":"file:\/F:\/Softwares\/jee-2022-12\/eclipse-workspace\/StaticContentInJSP\/src\/main\/webapp\/css\/helloCSS.css"},{"path":"\/JSPDirectives\/src\/main\/webapp","parentWorkspace":"F:\/Softwares\/jee-2022-12\/eclipse-workspace","name":"loginPage.jsp","lastModified":1675252401245,"locationURI":"file:\/F:\/Softwares\/jee-2022-12\/eclipse-workspace\/JSPDirectives\/src\/main\/webapp\/loginPage.jsp"}]}